{"v":4,"entries":{"configure-your-project--docs":{"id":"configure-your-project--docs","title":"Configure your project","name":"Docs","importPath":"./src/stories/Configure.mdx","storiesImports":[],"type":"docs","tags":["unattached-mdx","docs"]},"marks--axis":{"type":"story","id":"marks--axis","name":"Axis","title":"Marks","importPath":"./src/stories/Axis.stories.ts","tags":["story"]},"marks--bar":{"type":"story","id":"marks--bar","name":"Bar","title":"Marks","importPath":"./src/stories/Bar.stories.ts","tags":["story"]},"marks--grouped-bar":{"type":"story","id":"marks--grouped-bar","name":"Grouped Bar","title":"Marks","importPath":"./src/stories/Bar.stories.ts","tags":["story"]},"marks--stacked-bar":{"type":"story","id":"marks--stacked-bar","name":"Stacked Bar","title":"Marks","importPath":"./src/stories/Bar.stories.ts","tags":["story"]},"marks--box":{"type":"story","id":"marks--box","name":"Box","title":"Marks","importPath":"./src/stories/Box.stories.ts","tags":["story"]},"example-button--docs":{"id":"example-button--docs","title":"Example/Button","name":"Docs","importPath":"./src/stories/Button.stories.ts","type":"docs","tags":["autodocs","docs"],"storiesImports":[]},"example-button--primary":{"type":"story","id":"example-button--primary","name":"Primary","title":"Example/Button","importPath":"./src/stories/Button.stories.ts","tags":["autodocs","story"]},"example-button--secondary":{"type":"story","id":"example-button--secondary","name":"Secondary","title":"Example/Button","importPath":"./src/stories/Button.stories.ts","tags":["autodocs","story"]},"example-button--large":{"type":"story","id":"example-button--large","name":"Large","title":"Example/Button","importPath":"./src/stories/Button.stories.ts","tags":["autodocs","story"]},"example-button--small":{"type":"story","id":"example-button--small","name":"Small","title":"Example/Button","importPath":"./src/stories/Button.stories.ts","tags":["autodocs","story"]},"interface--button-group":{"type":"story","id":"interface--button-group","name":"Button Group","title":"Interface","importPath":"./src/stories/ButtonGroup.stories.ts","tags":["story"]},"interface--checkbox":{"type":"story","id":"interface--checkbox","name":"Checkbox","title":"Interface","importPath":"./src/stories/Checkbox.stories.ts","tags":["story"]},"interface--chips":{"type":"story","id":"interface--chips","name":"Chips","title":"Interface","importPath":"./src/stories/Chips.stories.ts","tags":["story"]},"interface--autocomplete-chips":{"type":"story","id":"interface--autocomplete-chips","name":"Autocomplete Chips","title":"Interface","importPath":"./src/stories/Chips.stories.ts","tags":["story"]},"marks--choropleth":{"type":"story","id":"marks--choropleth","name":"Choropleth","title":"Marks","importPath":"./src/stories/Choropleth.stories.ts","tags":["story"]},"marks--density-map":{"type":"story","id":"marks--density-map","name":"Density Map","title":"Marks","importPath":"./src/stories/DensityMap.stories.ts","tags":["story"]},"marks--dot":{"type":"story","id":"marks--dot","name":"Dot","title":"Marks","importPath":"./src/stories/Dot.stories.ts","tags":["story"]},"marks--complex-dot":{"type":"story","id":"marks--complex-dot","name":"Complex Dot","title":"Marks","importPath":"./src/stories/Dot.stories.ts","tags":["story"]},"marks--controlled-dot":{"type":"story","id":"marks--controlled-dot","name":"Controlled Dot","title":"Marks","importPath":"./src/stories/Dot.stories.ts","tags":["story"]},"marks--dot-map":{"type":"story","id":"marks--dot-map","name":"Dot Map","title":"Marks","importPath":"./src/stories/Dotmap.stories.ts","tags":["story"]},"data--download":{"type":"story","id":"data--download","name":"Download","title":"Data","importPath":"./src/stories/Download.stories.ts","tags":["story"]},"new--flex-box":{"type":"story","id":"new--flex-box","name":"Flex Box","title":"New","importPath":"./src/stories/FlexBox.stories.ts","tags":["story"]},"data--gl-map":{"type":"story","id":"data--gl-map","name":"Gl Map","title":"Data","importPath":"./src/stories/GlMap.stories.ts","tags":["story"]},"data--choro-test":{"type":"story","id":"data--choro-test","name":"Choro Test","title":"Data","importPath":"./src/stories/GlMap.stories.ts","tags":["story"]},"data--choropleth-map":{"type":"story","id":"data--choropleth-map","name":"Choropleth Map","title":"Data","importPath":"./src/stories/GlMap.stories.ts","tags":["story"]},"data--dot-map":{"type":"story","id":"data--dot-map","name":"Dot Map","title":"Data","importPath":"./src/stories/GlMap.stories.ts","tags":["story"]},"data--controlled-gl-map":{"type":"story","id":"data--controlled-gl-map","name":"Controlled Gl Map","title":"Data","importPath":"./src/stories/GlMap.stories.ts","tags":["story"]},"example-header--docs":{"id":"example-header--docs","title":"Example/Header","name":"Docs","importPath":"./src/stories/Header.stories.ts","type":"docs","tags":["autodocs","docs"],"storiesImports":[]},"example-header--logged-in":{"type":"story","id":"example-header--logged-in","name":"Logged In","title":"Example/Header","importPath":"./src/stories/Header.stories.ts","tags":["autodocs","story"]},"example-header--logged-out":{"type":"story","id":"example-header--logged-out","name":"Logged Out","title":"Example/Header","importPath":"./src/stories/Header.stories.ts","tags":["autodocs","story"]},"marks--heatmap":{"type":"story","id":"marks--heatmap","name":"Heatmap","title":"Marks","importPath":"./src/stories/Heatmap.stories.ts","tags":["story"]},"marks--histogram":{"type":"story","id":"marks--histogram","name":"Histogram","title":"Marks","importPath":"./src/stories/Histogram.stories.ts","tags":["story"]},"primitive--interface":{"type":"story","id":"primitive--interface","name":"Interface","title":"Primitive","importPath":"./src/stories/Interface.stories.ts","tags":["story"]},"marks--test-line":{"type":"story","id":"marks--test-line","name":"Test Line","title":"Marks","importPath":"./src/stories/Line.stories.ts","tags":["story"]},"marks--line":{"type":"story","id":"marks--line","name":"Line","title":"Marks","importPath":"./src/stories/Line.stories.ts","tags":["story"]},"marks--live-line":{"type":"story","id":"marks--live-line","name":"Live Line","title":"Marks","importPath":"./src/stories/Line.stories.ts","tags":["story"]},"new--modal":{"type":"story","id":"new--modal","name":"Modal","title":"New","importPath":"./src/stories/Modal.stories.ts","tags":["story"]},"example-page--logged-in":{"type":"story","id":"example-page--logged-in","name":"Logged In","title":"Example/Page","importPath":"./src/stories/Page.stories.ts","tags":["story"]},"example-page--logged-out":{"type":"story","id":"example-page--logged-out","name":"Logged Out","title":"Example/Page","importPath":"./src/stories/Page.stories.ts","tags":["story"]},"interface--param-view":{"type":"story","id":"interface--param-view","name":"Param View","title":"Interface","importPath":"./src/stories/ParamView.stories.ts","tags":["story"]},"projects--prevent-blindness":{"type":"story","id":"projects--prevent-blindness","name":"Prevent Blindness","title":"Projects","importPath":"./src/stories/Projects.stories.ts","tags":["story"]},"projects--eecrc":{"type":"story","id":"projects--eecrc","name":"EECRC","title":"Projects","importPath":"./src/stories/Projects.stories.ts","tags":["story"]},"projects--equiticity":{"type":"story","id":"projects--equiticity","name":"Equiticity","title":"Projects","importPath":"./src/stories/Projects.stories.ts","tags":["story"]},"projects--cpr-1":{"type":"story","id":"projects--cpr-1","name":"CPR 1","title":"Projects","importPath":"./src/stories/Projects.stories.ts","tags":["story"]},"projects--cpr-2":{"type":"story","id":"projects--cpr-2","name":"CPR 2","title":"Projects","importPath":"./src/stories/Projects.stories.ts","tags":["story"]},"projects--cpr-3":{"type":"story","id":"projects--cpr-3","name":"CPR 3","title":"Projects","importPath":"./src/stories/Projects.stories.ts","tags":["story"]},"projects--circulate-san-diego":{"type":"story","id":"projects--circulate-san-diego","name":"Circulate San Diego","title":"Projects","importPath":"./src/stories/Projects.stories.ts","tags":["story"]},"projects--circulate-san-diego-2":{"type":"story","id":"projects--circulate-san-diego-2","name":"Circulate San Diego 2","title":"Projects","importPath":"./src/stories/Projects.stories.ts","tags":["story"]},"projects--circulate-san-diego-3":{"type":"story","id":"projects--circulate-san-diego-3","name":"Circulate San Diego 3","title":"Projects","importPath":"./src/stories/Projects.stories.ts","tags":["story"]},"projects--wisconsin":{"type":"story","id":"projects--wisconsin","name":"Wisconsin","title":"Projects","importPath":"./src/stories/Projects.stories.ts","tags":["story"]},"projects--m-3":{"type":"story","id":"projects--m-3","name":"M 3","title":"Projects","importPath":"./src/stories/Projects.stories.ts","tags":["story"]},"interface--radio":{"type":"story","id":"interface--radio","name":"Radio","title":"Interface","importPath":"./src/stories/Radio.stories.ts","tags":["story"]},"marks--linear-regression-y":{"type":"story","id":"marks--linear-regression-y","name":"Linear Regression Y","title":"Marks","importPath":"./src/stories/Regression.stories.ts","tags":["story"]},"marks--linear-regression-x":{"type":"story","id":"marks--linear-regression-x","name":"Linear Regression X","title":"Marks","importPath":"./src/stories/Regression.stories.ts","tags":["story"]},"marks--rule-x":{"type":"story","id":"marks--rule-x","name":"Rule X","title":"Marks","importPath":"./src/stories/Rule.stories.ts","tags":["story"]},"marks--rule-x-data":{"type":"story","id":"marks--rule-x-data","name":"Rule X Data","title":"Marks","importPath":"./src/stories/Rule.stories.ts","tags":["story"]},"marks--rule-y":{"type":"story","id":"marks--rule-y","name":"Rule Y","title":"Marks","importPath":"./src/stories/Rule.stories.ts","tags":["story"]},"marks--rule-y-data":{"type":"story","id":"marks--rule-y-data","name":"Rule Y Data","title":"Marks","importPath":"./src/stories/Rule.stories.ts","tags":["story"]},"marks--rule-bound":{"type":"story","id":"marks--rule-bound","name":"Rule Bound","title":"Marks","importPath":"./src/stories/Rule.stories.ts","tags":["story"]},"interface--select":{"type":"story","id":"interface--select","name":"Select","title":"Interface","importPath":"./src/stories/Select.stories.ts","tags":["story"]},"interface--slider":{"type":"story","id":"interface--slider","name":"Slider","title":"Interface","importPath":"./src/stories/Slider.stories.ts","tags":["story"]},"data--stat":{"type":"story","id":"data--stat","name":"Stat","title":"Data","importPath":"./src/stories/Stat.stories.ts","tags":["story"]},"data--stat-table":{"type":"story","id":"data--stat-table","name":"Stat Table","title":"Data","importPath":"./src/stories/StatTable.stories.ts","tags":["story"]},"interface--switch":{"type":"story","id":"interface--switch","name":"Switch","title":"Interface","importPath":"./src/stories/Switch.stories.ts","tags":["story"]},"data--table":{"type":"story","id":"data--table","name":"Table","title":"Data","importPath":"./src/stories/Table.stories.ts","tags":["story"]},"data--controlled-table":{"type":"story","id":"data--controlled-table","name":"Controlled Table","title":"Data","importPath":"./src/stories/Table.stories.ts","tags":["story"]},"new--tabs":{"type":"story","id":"new--tabs","name":"Tabs","title":"New","importPath":"./src/stories/Tabs.stories.ts","tags":["story"]},"marks--density":{"type":"story","id":"marks--density","name":"Density","title":"Marks","importPath":"./src/stories/projects/Density.stories.ts","tags":["story"]}}}
